setupext_janitor/__init__.py
setupext_janitor/janitor.py
setupext_janitor-1.1.2.dist-info/LICENSE
setupext_janitor-1.1.2.dist-info/METADATA
setupext_janitor-1.1.2.dist-info/WHEEL
setupext_janitor-1.1.2.dist-info/entry_points.txt
setupext_janitor-1.1.2.dist-info/top_level.txt
setupext_janitor-1.1.2.dist-info/zip-safe
setupext_janitor-1.1.2.dist-info/RECORD
