Metadata-Version: 2.1
Name: setupext-janitor
Version: 1.1.2
Summary: Making setup.py clean more useful.
Home-page: http://github.com/dave-shawley/setupext-janitor
Author: Dave Shawley
Author-email: daveshawley@gmail.com
License: UNKNOWN
Platform: any
Classifier: Intended Audience :: Developers
Classifier: License :: OSI Approved :: BSD License
Classifier: Operating System :: OS Independent
Classifier: Programming Language :: Python :: 2.7
Classifier: Programming Language :: Python :: 3.5
Classifier: Programming Language :: Python :: 3.6
Classifier: Programming Language :: Python :: 3.7
Classifier: Programming Language :: Python :: 3.8
Classifier: Framework :: Setuptools Plugin
Classifier: Development Status :: 5 - Production/Stable
Requires-Python: >=2.7, !=3.0.*, !=3.1.*, !=3.2.*, !=3.3.*, != 3.4.*
Provides-Extra: dev
Requires-Dist: coverage (==4.5.3) ; extra == 'dev'
Requires-Dist: flake8 (==3.7.7) ; extra == 'dev'
Requires-Dist: nose (==1.3.7) ; extra == 'dev'
Requires-Dist: sphinx (==1.8.5) ; extra == 'dev'
Requires-Dist: sphinx-rtd-theme (==0.4.3) ; extra == 'dev'
Requires-Dist: tox (==3.9.0) ; extra == 'dev'
Requires-Dist: mock (==1.0.1) ; (python_version < "3") and extra == 'dev'
